rfCloudTest/__init__.py
rfCloudTest/cloudTestMain.py
rfCloudTest/business/__init__.py
rfCloudTest/business/parseCaseUtils.py
rfCloudTest/business/parseHttpStep.py
rfCloudTest/business/parseKeywordUtils.py
rfCloudTest/business/parseSetupTeardownUtils.py
rfCloudTest/business/parseSuiteUtils.py
rfCloudTest/business/parseTagUtils.py
rfCloudTest/business/parseVariableUtils.py
rfCloudTest/business/robotFileUtils.py
rfCloudTest/rfctHttpStep/__init__.py
rfCloudTest/rfctHttpStep/rfctHttpStepMain.py
rfCloudTest/rfctMysqlStep/__init__.py
rfCloudTest/rfctMysqlStep/rfctMysqlStepMain.py
rfCloudTest/rfctStep/__init__.py
rfCloudTest/rfctStep/rfctStepMain.py
rfCloudTest/rfctStep/xfctRftStepMain.py
rfCloudTest/utils/__init__.py
rfCloudTest/utils/fileUtils.py
rfCloudTest/utils/jsonAndYamlUtils.py
rfCloudTest/utils/mappingUtils.py
rfCloudTest/utils/statusObj.py
rfCloudTest/utils/typeUtils.py
rfCloudTest/xfctRftStep/__init__.py
rfCloudTest/xfctRftStep/xfctRftStepMain.py
rfCloudTest-0.0.15.dist-info/METADATA
rfCloudTest-0.0.15.dist-info/WHEEL
rfCloudTest-0.0.15.dist-info/entry_points.txt
rfCloudTest-0.0.15.dist-info/top_level.txt
rfCloudTest-0.0.15.dist-info/RECORD
