Metadata-Version: 2.1
Name: rfCloudTest
Version: 0.0.15
Summary: robot framework自动化开发基础库:添加mysql处理库
Home-page: UNKNOWN
Author: wu weiping
Author-email: 115773673@qq.com
License: UNKNOWN
Platform: UNKNOWN
Requires-Python: >=3.6
Requires-Dist: rfApiTestLibrary
